stbook/__init__.py
stbook/app.py
stbook/cli.py
stbook/code_completion.py
stbook/code_runner.py
stbook-0.0.1.dist-info/LICENSE
stbook-0.0.1.dist-info/METADATA
stbook-0.0.1.dist-info/WHEEL
stbook-0.0.1.dist-info/entry_points.txt
stbook-0.0.1.dist-info/top_level.txt
stbook-0.0.1.dist-info/RECORD
