Metadata-Version: 2.1
Name: stbook
Version: 0.0.1
Summary: Streamlit Notebook - imagine Jupyter Notebook within Streamlit.
Home-page: https://github.com/iamaziz/stbook
Author: Aziz Alto
Author-email: iamaziz.alto@gmail.com
Classifier: Programming Language :: Python :: 3
Classifier: License :: OSI Approved :: MIT License
Classifier: Operating System :: OS Independent
Requires-Python: >=3.6
License-File: LICENSE
Requires-Dist: streamlit
Requires-Dist: streamlit-code-editor
Requires-Dist: ollama
